qmap/__init__.py
qmap/globals.py
qmap/main.py
qmap/manager.py
qmap/profile.py
qmap/template.py
qmap/utils.py
qmap/executor/__init__.py
qmap/executor/dummy.py
qmap/executor/executor.py
qmap/executor/local.py
qmap/executor/lsf.py
qmap/executor/sge.py
qmap/executor/slurm.py
qmap/executor/profiles/default.conf
qmap/executor/profiles/local.conf
qmap/executor/profiles/lsf.conf
qmap/executor/profiles/profile.conf.spec
qmap/executor/profiles/sge.conf
qmap/executor/profiles/slurm.conf
qmap/executor/profiles/test.conf
qmap/file/__init__.py
qmap/file/env.py
qmap/file/jobs.py
qmap/file/metadata.py
qmap/job/__init__.py
qmap/job/job.py
qmap/job/parameters.py
qmap/job/status.py
qmap/view/__init__.py
qmap/view/console.py
qmap/view/plain.py
qmap-0.4.1.dist-info/licenses/LICENSE.txt
qmap-0.4.1.dist-info/METADATA
qmap-0.4.1.dist-info/WHEEL
qmap-0.4.1.dist-info/entry_points.txt
qmap-0.4.1.dist-info/top_level.txt
qmap-0.4.1.dist-info/RECORD
