Metadata-Version: 2.4
Name: qmap
Version: 0.4.1
Summary: Manage job executions in a cluster
Home-page: https://github.com/bbglab/qmap
Author: Barcelona Biomedical Genomics Lab
Author-email: bbglab@irbbarcelona.org
License: Apache Software License 2.0
Classifier: License :: OSI Approved :: Apache Software License
Classifier: Programming Language :: Python :: 3
License-File: LICENSE.txt
Requires-Dist: bgconfig>=0.8
Requires-Dist: click>=6.7
Requires-Dist: configobj>=5.0.6
Requires-Dist: psutil>=5.4.7
Requires-Dist: urwid>=1.3.1
Dynamic: author
Dynamic: author-email
Dynamic: classifier
Dynamic: description
Dynamic: description-content-type
Dynamic: home-page
Dynamic: license
Dynamic: license-file
Dynamic: requires-dist
Dynamic: summary
